hive/chat/__init__.py
hive/chat/__version__.py
hive/chat/matrix.py
hive/chat/message.py
hive/chat/util.py
hive/chat/v1.py
hive/chat/v1_matrix.py
hive/chat/v2.py
hive_chat-0.1.4.dist-info/METADATA
hive_chat-0.1.4.dist-info/WHEEL
hive_chat-0.1.4.dist-info/top_level.txt
hive_chat-0.1.4.dist-info/RECORD
