Metadata-Version: 2.4
Name: hive-chat
Version: 0.1.4
Summary: Chatbot interface for Hive
Author-email: Gary Benson <gary@gbenson.net>
Project-URL: Homepage, https://github.com/gbenson/hive/tree/main/libs/chat
Project-URL: Source, https://github.com/gbenson/hive
Classifier: License :: OSI Approved :: MIT License
Requires-Dist: hive-common>=0.1.3
Requires-Dist: hive-messaging>=0.13.0
Requires-Dist: pydantic
